conecta-0.0.7.dist-info/METADATA
conecta-0.0.7.dist-info/WHEEL
conecta.libs/libgcc_s-98a1ef30.so.1
conecta/__init__.py
conecta/conecta.cpython-313-x86_64-linux-musl.so
conecta/ext/__init__.py
conecta/tests/conftest.py
conecta/tests/databases/test_postgres.py
conecta/tests/test_bind.py
conecta/tests/test_data/lineitem_ddl.sql
conecta/tests/test_data/lineitem_small.sql
conecta/tests/test_data/pg_datatypes_data.sql
conecta/tests/test_data/pg_datatypes_ddl.sql
conecta/tests/test_data/pg_datatypes_select.sql
conecta/tests/test_data/pg_postgis_datatypes_data.sql
conecta/tests/test_data/pg_postgis_datatypes_ddl.sql
conecta/tests/test_data/pg_postgis_datatypes_select.sql
conecta/tests/test_ext_polars.py
conecta/tests/test_partition_plan.py
conecta/tests/test_read_sql.py
conecta-0.0.7.dist-info/RECORD
