Metadata-Version: 2.4
Name: conecta
Version: 0.0.7
Classifier: Development Status :: 3 - Alpha
Classifier: Environment :: Console
Classifier: License :: OSI Approved :: MIT License
Classifier: Operating System :: OS Independent
Classifier: Programming Language :: Python :: Implementation :: CPython
Classifier: Programming Language :: Python :: Implementation :: PyPy
Classifier: Programming Language :: Python :: 3 :: Only
Classifier: Programming Language :: Python :: 3.10
Classifier: Programming Language :: Python :: 3.11
Classifier: Programming Language :: Python :: 3.12
Classifier: Programming Language :: Python :: 3.13
Classifier: Programming Language :: Python :: 3.14
Classifier: Programming Language :: Rust
Classifier: Topic :: Scientific/Engineering
Classifier: Typing :: Typed
Summary: Load data from SQL databases to Arrow
Keywords: arrow,databases,sql,dataframe
Author-email: surister <surister98@gmail.com>
Requires-Python: >=3.10
Project-URL: Homepage, https://github.com/surister/conecta/
Project-URL: Documentation, https://conecta.surister.dev/
Project-URL: Repository, https://github.com/surister/conecta/
Project-URL: Changelog, https://github.com/surister/conecta/releases
